[
{
    "model": "mailing.recipient",
    "pk": 5,
    "fields": {
        "email": "skypro1@mailinator.com",
        "full_name": "Скайпро Скайпрошович",
        "owner": 12,
        "comment": "skypro1@mailinator.com.\r\nСкайпро Скайпрошович.\r\nТестовый ящик: после пробной рассылки зайди на mailinator.com и вбей название ящика."
    }
},
{
    "model": "mailing.recipient",
    "pk": 6,
    "fields": {
        "email": "skypro2@mailinator.com",
        "full_name": "Скайпро Скайпрошович",
        "owner": 12,
        "comment": "skypro2@mailinator.com.\r\nСкайпро Скайпрошович.\r\nТестовый ящик: после пробной рассылки зайди на mailinator.com и вбей название ящика."
    }
},
{
    "model": "mailing.recipient",
    "pk": 7,
    "fields": {
        "email": "skypro3@mailinator.com",
        "full_name": "Скайпро Скайпрошович",
        "owner": 12,
        "comment": "skypro3@mailinator.com. Скайпро Скайпрошович. Тестовый ящик: после пробной рассылки зайди на mailinator.com и вбей название ящика."
    }
},
{
    "model": "mailing.recipient",
    "pk": 8,
    "fields": {
        "email": "skypro4@mailinatorrrr.ccccom",
        "full_name": "Скайпро Скайпрошович",
        "owner": 12,
        "comment": "Плохой ящик для неудачной рассылки skypro4@mailinator.com. Скайпро Скайпрошович. Тестовый ящик: после пробной рассылки зайди на mailinator.com и вбей название ящика."
    }
},
{
    "model": "mailing.recipient",
    "pk": 9,
    "fields": {
        "email": "skypro5@mailinator.com",
        "full_name": "Скайпро Скайпрошович",
        "owner": 12,
        "comment": "skypro5@mailinator.com. Скайпро Скайпрошович. Тестовый ящик: после пробной рассылки зайди на mailinator.com и вбей название ящика."
    }
},
{
    "model": "mailing.recipient",
    "pk": 10,
    "fields": {
        "email": "skypro6@mailinator.com",
        "full_name": "Скайпро Скайпрошович",
        "owner": 12,
        "comment": "skypro6@mailinator.com. Скайпро Скайпрошович. Тестовый ящик: после пробной рассылки зайди на mailinator.com и вбей название ящика."
    }
},
{
    "model": "mailing.recipient",
    "pk": 11,
    "fields": {
        "email": "skypro7@mailinator.com",
        "full_name": "Скайпро Скайпрошович",
        "owner": 12,
        "comment": "skypro7@mailinator.com. Скайпро Скайпрошович. Тестовый ящик: после пробной рассылки зайди на mailinator.com и вбей название ящика."
    }
},
{
    "model": "mailing.recipient",
    "pk": 12,
    "fields": {
        "email": "skypro10@linator.commmm",
        "full_name": "Скайпро Скайпрошович",
        "owner": 12,
        "comment": "Плохой ящик для неудачной рассылки skypro10@linator.commmm. Скайпро Скайпрошович. Тестовый ящик: после пробной рассылки зайди на mailinator.com и вбей название ящика."
    }
},
{
    "model": "mailing.recipient",
    "pk": 13,
    "fields": {
        "email": "skypro8@mailinator.com",
        "full_name": "Скайпро Скайпрошович",
        "owner": 12,
        "comment": "skypro8@mailinator.com. Скайпро Скайпрошович. Тестовый ящик: после пробной рассылки зайди на mailinator.com и вбей название ящика."
    }
},
{
    "model": "mailing.recipient",
    "pk": 14,
    "fields": {
        "email": "skypro9@mailinator.com",
        "full_name": "Скайпро Скайпрошович",
        "owner": 12,
        "comment": "skypro9@mailinator.com. Скайпро Скайпрошович. Тестовый ящик: после пробной рассылки зайди на mailinator.com и вбей название ящика."
    }
},
{
    "model": "mailing.recipient",
    "pk": 15,
    "fields": {
        "email": "qwerty@asdf.ru",
        "full_name": "qwerty asdf",
        "owner": 13,
        "comment": "Тестовый получатель для пользователя test2@test2.ru"
    }
},
{
    "model": "mailing.recipient",
    "pk": 16,
    "fields": {
        "email": "2@2.ry",
        "full_name": "123456",
        "owner": 11,
        "comment": "76543"
    }
},
{
    "model": "mailing.recipient",
    "pk": 17,
    "fields": {
        "email": "3@3.jhkgn",
        "full_name": "765y4rthyugmk",
        "owner": 11,
        "comment": "t7rr7juuy"
    }
}
]
